data_engine/__init__.py
data_engine/define.py
data_engine/core/__init__.py
data_engine/core/base.py
data_engine/core/executors.py
data_engine/core/factory.py
data_engine/executors/__init__.py
data_engine/executors/ray_executor.py
data_engine/executors/spark_executor.py
data_engine/processors/__init__.py
data_engine/processors/register.py
data_engine/processors/audio/__init__.py
data_engine/processors/audio/audio_filter_duration.py
data_engine/processors/audio/audio_filter_nmf_snr.py
data_engine/processors/audio/audio_filter_size.py
data_engine/processors/audio/audio_mapper_fixed_duration_segmenter.py
data_engine/processors/audio/audio_mapper_timestamp_segmenter.py
data_engine/processors/nlp/__init__.py
data_engine/processors/nlp/nlp_dedup_minhash.py
data_engine/processors/nlp/nlp_filter_action.py
data_engine/processors/nlp/nlp_filter_alphanumeric.py
data_engine/processors/nlp/nlp_filter_avg_line_length.py
data_engine/processors/nlp/nlp_filter_calculate_diversity_assessment.py
data_engine/processors/nlp/nlp_filter_calculate_entropy.py
data_engine/processors/nlp/nlp_filter_calculate_loss_single.py
data_engine/processors/nlp/nlp_filter_calculate_tags.py
data_engine/processors/nlp/nlp_filter_check_synthetic_data_quality.py
data_engine/processors/nlp/nlp_filter_compressibility_ratio.py
data_engine/processors/nlp/nlp_filter_curriculum.py
data_engine/processors/nlp/nlp_filter_data_diversity.py
data_engine/processors/nlp/nlp_filter_data_information.py
data_engine/processors/nlp/nlp_filter_data_leak.py
data_engine/processors/nlp/nlp_filter_data_optimization.py
data_engine/processors/nlp/nlp_filter_detect_knowledge_deficiency.py
data_engine/processors/nlp/nlp_filter_entity_count.py
data_engine/processors/nlp/nlp_filter_entity_dependency.py
data_engine/processors/nlp/nlp_filter_evol_filter.py
data_engine/processors/nlp/nlp_filter_flagged_words.py
data_engine/processors/nlp/nlp_filter_hierarchical_tags.py
data_engine/processors/nlp/nlp_filter_industry_classification.py
data_engine_tes1-0.1.5.dist-info/METADATA
data_engine_tes1-0.1.5.dist-info/WHEEL
data_engine_tes1-0.1.5.dist-info/top_level.txt
data_engine_tes1-0.1.5.dist-info/RECORD
